{"Time":"2018-10-24T12:32:59.630853687+07:00","Action":"run","Package":"template/models/logic/svclog","Test":"TestInsertServiceLog"}
{"Time":"2018-10-24T12:32:59.630980097+07:00","Action":"output","Package":"template/models/logic/svclog","Test":"TestInsertServiceLog","Output":"=== RUN   TestInsertServiceLog\n"}
{"Time":"2018-10-24T12:32:59.630987852+07:00","Action":"output","Package":"template/models/logic/svclog","Test":"TestInsertServiceLog","Output":"[ORM]2018/10/24 12:30:55  -[Queries/default] - [  OK /  db.BeginTx /     0.0ms] - [START TRANSACTION]\n"}
{"Time":"2018-10-24T12:32:59.630992715+07:00","Action":"output","Package":"template/models/logic/svclog","Test":"TestInsertServiceLog","Output":"[ORM]2018/10/24 12:30:55  -[Queries/default] - [  OK /   tx.Commit /     0.1ms] - [COMMIT]\n"}
{"Time":"2018-10-24T12:32:59.630997001+07:00","Action":"output","Package":"template/models/logic/svclog","Test":"TestInsertServiceLog","Output":"\n"}
{"Time":"2018-10-24T12:32:59.631001666+07:00","Action":"output","Package":"template/models/logic/svclog","Test":"TestInsertServiceLog","Output":"  TestInsertServiceLog \n"}
{"Time":"2018-10-24T12:32:59.631005532+07:00","Action":"output","Package":"template/models/logic/svclog","Test":"TestInsertServiceLog","Output":"    Should Success \u001b[32m✔\u001b[0m\n"}
{"Time":"2018-10-24T12:32:59.631009684+07:00","Action":"output","Package":"template/models/logic/svclog","Test":"TestInsertServiceLog","Output":"\n"}
{"Time":"2018-10-24T12:32:59.631013434+07:00","Action":"output","Package":"template/models/logic/svclog","Test":"TestInsertServiceLog","Output":"\u001b[31m\u001b[0m\u001b[33m\u001b[0m\u001b[32m\n"}
{"Time":"2018-10-24T12:32:59.631017993+07:00","Action":"output","Package":"template/models/logic/svclog","Test":"TestInsertServiceLog","Output":"1 total assertion\u001b[0m\n"}
{"Time":"2018-10-24T12:32:59.631023701+07:00","Action":"output","Package":"template/models/logic/svclog","Test":"TestInsertServiceLog","Output":"\n"}
{"Time":"2018-10-24T12:32:59.631029706+07:00","Action":"output","Package":"template/models/logic/svclog","Test":"TestInsertServiceLog","Output":"--- PASS: TestInsertServiceLog (0.00s)\n"}
{"Time":"2018-10-24T12:32:59.631034117+07:00","Action":"pass","Package":"template/models/logic/svclog","Test":"TestInsertServiceLog","Elapsed":0}
{"Time":"2018-10-24T12:32:59.631039108+07:00","Action":"run","Package":"template/models/logic/svclog","Test":"TestGetAllServiceLog"}
{"Time":"2018-10-24T12:32:59.631042576+07:00","Action":"output","Package":"template/models/logic/svclog","Test":"TestGetAllServiceLog","Output":"=== RUN   TestGetAllServiceLog\n"}
{"Time":"2018-10-24T12:32:59.631046353+07:00","Action":"output","Package":"template/models/logic/svclog","Test":"TestGetAllServiceLog","Output":"\n"}
{"Time":"2018-10-24T12:32:59.631050116+07:00","Action":"output","Package":"template/models/logic/svclog","Test":"TestGetAllServiceLog","Output":"  TestGetAllServiceLog \n"}
{"Time":"2018-10-24T12:32:59.63105383+07:00","Action":"output","Package":"template/models/logic/svclog","Test":"TestGetAllServiceLog","Output":"    Should Success \u001b[32m✔\u001b[0m\u001b[32m✔\u001b[0m\n"}
{"Time":"2018-10-24T12:32:59.6310578+07:00","Action":"output","Package":"template/models/logic/svclog","Test":"TestGetAllServiceLog","Output":"\n"}
{"Time":"2018-10-24T12:32:59.631061507+07:00","Action":"output","Package":"template/models/logic/svclog","Test":"TestGetAllServiceLog","Output":"\u001b[31m\u001b[0m\u001b[33m\u001b[0m\u001b[32m\n"}
{"Time":"2018-10-24T12:32:59.631065339+07:00","Action":"output","Package":"template/models/logic/svclog","Test":"TestGetAllServiceLog","Output":"3 total assertions\u001b[0m\n"}
{"Time":"2018-10-24T12:32:59.631069492+07:00","Action":"output","Package":"template/models/logic/svclog","Test":"TestGetAllServiceLog","Output":"\n"}
{"Time":"2018-10-24T12:32:59.631073866+07:00","Action":"output","Package":"template/models/logic/svclog","Test":"TestGetAllServiceLog","Output":"--- PASS: TestGetAllServiceLog (0.00s)\n"}
{"Time":"2018-10-24T12:32:59.631077931+07:00","Action":"pass","Package":"template/models/logic/svclog","Test":"TestGetAllServiceLog","Elapsed":0}
{"Time":"2018-10-24T12:32:59.631084706+07:00","Action":"run","Package":"template/models/logic/svclog","Test":"TestGetOneByJobIDServiceLog"}
{"Time":"2018-10-24T12:32:59.631088563+07:00","Action":"output","Package":"template/models/logic/svclog","Test":"TestGetOneByJobIDServiceLog","Output":"=== RUN   TestGetOneByJobIDServiceLog\n"}
{"Time":"2018-10-24T12:32:59.631092354+07:00","Action":"output","Package":"template/models/logic/svclog","Test":"TestGetOneByJobIDServiceLog","Output":"\n"}
{"Time":"2018-10-24T12:32:59.631096342+07:00","Action":"output","Package":"template/models/logic/svclog","Test":"TestGetOneByJobIDServiceLog","Output":"  TestGetOneByJobIDServiceLog \n"}
{"Time":"2018-10-24T12:32:59.631100216+07:00","Action":"output","Package":"template/models/logic/svclog","Test":"TestGetOneByJobIDServiceLog","Output":"    Should Success \u001b[32m✔\u001b[0m\u001b[32m✔\u001b[0m\n"}
{"Time":"2018-10-24T12:32:59.631104013+07:00","Action":"output","Package":"template/models/logic/svclog","Test":"TestGetOneByJobIDServiceLog","Output":"\n"}
{"Time":"2018-10-24T12:32:59.631107676+07:00","Action":"output","Package":"template/models/logic/svclog","Test":"TestGetOneByJobIDServiceLog","Output":"\u001b[31m\u001b[0m\u001b[33m\u001b[0m\u001b[32m\n"}
{"Time":"2018-10-24T12:32:59.631111487+07:00","Action":"output","Package":"template/models/logic/svclog","Test":"TestGetOneByJobIDServiceLog","Output":"5 total assertions\u001b[0m\n"}
{"Time":"2018-10-24T12:32:59.63111516+07:00","Action":"output","Package":"template/models/logic/svclog","Test":"TestGetOneByJobIDServiceLog","Output":"\n"}
{"Time":"2018-10-24T12:32:59.631119439+07:00","Action":"output","Package":"template/models/logic/svclog","Test":"TestGetOneByJobIDServiceLog","Output":"--- PASS: TestGetOneByJobIDServiceLog (0.00s)\n"}
{"Time":"2018-10-24T12:32:59.631123484+07:00","Action":"pass","Package":"template/models/logic/svclog","Test":"TestGetOneByJobIDServiceLog","Elapsed":0}
{"Time":"2018-10-24T12:32:59.63112707+07:00","Action":"run","Package":"template/models/logic/svclog","Test":"TestUpdateByJobIDServiceLog"}
{"Time":"2018-10-24T12:32:59.631130492+07:00","Action":"output","Package":"template/models/logic/svclog","Test":"TestUpdateByJobIDServiceLog","Output":"=== RUN   TestUpdateByJobIDServiceLog\n"}
{"Time":"2018-10-24T12:32:59.631134432+07:00","Action":"output","Package":"template/models/logic/svclog","Test":"TestUpdateByJobIDServiceLog","Output":"[ORM]2018/10/24 12:30:55  -[Queries/default] - [  OK /  db.BeginTx /     0.0ms] - [START TRANSACTION]\n"}
{"Time":"2018-10-24T12:32:59.631138513+07:00","Action":"output","Package":"template/models/logic/svclog","Test":"TestUpdateByJobIDServiceLog","Output":"[ORM]2018/10/24 12:30:55  -[Queries/default] - [  OK /   tx.Commit /     0.0ms] - [COMMIT]\n"}
{"Time":"2018-10-24T12:32:59.631142397+07:00","Action":"output","Package":"template/models/logic/svclog","Test":"TestUpdateByJobIDServiceLog","Output":"\n"}
{"Time":"2018-10-24T12:32:59.631146098+07:00","Action":"output","Package":"template/models/logic/svclog","Test":"TestUpdateByJobIDServiceLog","Output":"  TestUpdateByJobIDServiceLog \n"}
{"Time":"2018-10-24T12:32:59.631149943+07:00","Action":"output","Package":"template/models/logic/svclog","Test":"TestUpdateByJobIDServiceLog","Output":"    Should Success \u001b[32m✔\u001b[0m\n"}
{"Time":"2018-10-24T12:32:59.631153717+07:00","Action":"output","Package":"template/models/logic/svclog","Test":"TestUpdateByJobIDServiceLog","Output":"\n"}
{"Time":"2018-10-24T12:32:59.631158142+07:00","Action":"output","Package":"template/models/logic/svclog","Test":"TestUpdateByJobIDServiceLog","Output":"\u001b[31m\u001b[0m\u001b[33m\u001b[0m\u001b[32m\n"}
{"Time":"2018-10-24T12:32:59.631163173+07:00","Action":"output","Package":"template/models/logic/svclog","Test":"TestUpdateByJobIDServiceLog","Output":"6 total assertions\u001b[0m\n"}
{"Time":"2018-10-24T12:32:59.631169597+07:00","Action":"output","Package":"template/models/logic/svclog","Test":"TestUpdateByJobIDServiceLog","Output":"\n"}
{"Time":"2018-10-24T12:32:59.631178945+07:00","Action":"output","Package":"template/models/logic/svclog","Test":"TestUpdateByJobIDServiceLog","Output":"--- PASS: TestUpdateByJobIDServiceLog (0.00s)\n"}
{"Time":"2018-10-24T12:32:59.631183741+07:00","Action":"pass","Package":"template/models/logic/svclog","Test":"TestUpdateByJobIDServiceLog","Elapsed":0}
{"Time":"2018-10-24T12:32:59.631187651+07:00","Action":"run","Package":"template/models/logic/svclog","Test":"TestUpdateReturnByJobIDServiceLog"}
{"Time":"2018-10-24T12:32:59.631191507+07:00","Action":"output","Package":"template/models/logic/svclog","Test":"TestUpdateReturnByJobIDServiceLog","Output":"=== RUN   TestUpdateReturnByJobIDServiceLog\n"}
{"Time":"2018-10-24T12:32:59.631197398+07:00","Action":"output","Package":"template/models/logic/svclog","Test":"TestUpdateReturnByJobIDServiceLog","Output":"[ORM]2018/10/24 12:30:55  -[Queries/default] - [  OK /  db.BeginTx /     0.0ms] - [START TRANSACTION]\n"}
{"Time":"2018-10-24T12:32:59.631202582+07:00","Action":"output","Package":"template/models/logic/svclog","Test":"TestUpdateReturnByJobIDServiceLog","Output":"[ORM]2018/10/24 12:30:55  -[Queries/default] - [  OK /   tx.Commit /     0.1ms] - [COMMIT]\n"}
{"Time":"2018-10-24T12:32:59.631206993+07:00","Action":"output","Package":"template/models/logic/svclog","Test":"TestUpdateReturnByJobIDServiceLog","Output":"\n"}
{"Time":"2018-10-24T12:32:59.631210861+07:00","Action":"output","Package":"template/models/logic/svclog","Test":"TestUpdateReturnByJobIDServiceLog","Output":"  TestUpdateReturnByJobIDServiceLog \n"}
{"Time":"2018-10-24T12:32:59.631214675+07:00","Action":"output","Package":"template/models/logic/svclog","Test":"TestUpdateReturnByJobIDServiceLog","Output":"    Should Success \u001b[32m✔\u001b[0m\u001b[32m✔\u001b[0m\n"}
{"Time":"2018-10-24T12:32:59.631218653+07:00","Action":"output","Package":"template/models/logic/svclog","Test":"TestUpdateReturnByJobIDServiceLog","Output":"\n"}
{"Time":"2018-10-24T12:32:59.631222468+07:00","Action":"output","Package":"template/models/logic/svclog","Test":"TestUpdateReturnByJobIDServiceLog","Output":"\u001b[31m\u001b[0m\u001b[33m\u001b[0m\u001b[32m\n"}
{"Time":"2018-10-24T12:32:59.631226553+07:00","Action":"output","Package":"template/models/logic/svclog","Test":"TestUpdateReturnByJobIDServiceLog","Output":"8 total assertions\u001b[0m\n"}
{"Time":"2018-10-24T12:32:59.631230355+07:00","Action":"output","Package":"template/models/logic/svclog","Test":"TestUpdateReturnByJobIDServiceLog","Output":"\n"}
{"Time":"2018-10-24T12:32:59.631234437+07:00","Action":"output","Package":"template/models/logic/svclog","Test":"TestUpdateReturnByJobIDServiceLog","Output":"--- PASS: TestUpdateReturnByJobIDServiceLog (0.00s)\n"}
{"Time":"2018-10-24T12:32:59.631238593+07:00","Action":"pass","Package":"template/models/logic/svclog","Test":"TestUpdateReturnByJobIDServiceLog","Elapsed":0}
{"Time":"2018-10-24T12:32:59.63124216+07:00","Action":"run","Package":"template/models/logic/svclog","Test":"TestDeleteByJobIDServiceLog"}
{"Time":"2018-10-24T12:32:59.631245541+07:00","Action":"output","Package":"template/models/logic/svclog","Test":"TestDeleteByJobIDServiceLog","Output":"=== RUN   TestDeleteByJobIDServiceLog\n"}
{"Time":"2018-10-24T12:32:59.631249549+07:00","Action":"output","Package":"template/models/logic/svclog","Test":"TestDeleteByJobIDServiceLog","Output":"[ORM]2018/10/24 12:30:55  -[Queries/default] - [  OK /  db.BeginTx /     0.0ms] - [START TRANSACTION]\n"}
{"Time":"2018-10-24T12:32:59.631253354+07:00","Action":"output","Package":"template/models/logic/svclog","Test":"TestDeleteByJobIDServiceLog","Output":"[ORM]2018/10/24 12:30:55  -[Queries/default] - [  OK /   tx.Commit /     0.1ms] - [COMMIT]\n"}
{"Time":"2018-10-24T12:32:59.631257037+07:00","Action":"output","Package":"template/models/logic/svclog","Test":"TestDeleteByJobIDServiceLog","Output":"\n"}
{"Time":"2018-10-24T12:32:59.631260638+07:00","Action":"output","Package":"template/models/logic/svclog","Test":"TestDeleteByJobIDServiceLog","Output":"  TestDeleteByJobIDServiceLog \n"}
{"Time":"2018-10-24T12:32:59.631267023+07:00","Action":"output","Package":"template/models/logic/svclog","Test":"TestDeleteByJobIDServiceLog","Output":"    Should Success \u001b[32m✔\u001b[0m\n"}
{"Time":"2018-10-24T12:32:59.631270996+07:00","Action":"output","Package":"template/models/logic/svclog","Test":"TestDeleteByJobIDServiceLog","Output":"\n"}
{"Time":"2018-10-24T12:32:59.631274705+07:00","Action":"output","Package":"template/models/logic/svclog","Test":"TestDeleteByJobIDServiceLog","Output":"\u001b[31m\u001b[0m\u001b[33m\u001b[0m\u001b[32m\n"}
{"Time":"2018-10-24T12:32:59.631278566+07:00","Action":"output","Package":"template/models/logic/svclog","Test":"TestDeleteByJobIDServiceLog","Output":"9 total assertions\u001b[0m\n"}
{"Time":"2018-10-24T12:32:59.631282312+07:00","Action":"output","Package":"template/models/logic/svclog","Test":"TestDeleteByJobIDServiceLog","Output":"\n"}
{"Time":"2018-10-24T12:32:59.631287088+07:00","Action":"output","Package":"template/models/logic/svclog","Test":"TestDeleteByJobIDServiceLog","Output":"--- PASS: TestDeleteByJobIDServiceLog (0.00s)\n"}
{"Time":"2018-10-24T12:32:59.631290781+07:00","Action":"pass","Package":"template/models/logic/svclog","Test":"TestDeleteByJobIDServiceLog","Elapsed":0}
{"Time":"2018-10-24T12:32:59.631294742+07:00","Action":"output","Package":"template/models/logic/svclog","Output":"PASS\n"}
{"Time":"2018-10-24T12:32:59.631298911+07:00","Action":"output","Package":"template/models/logic/svclog","Output":"coverage: 54.7% of statements\n"}
{"Time":"2018-10-24T12:32:59.63130297+07:00","Action":"output","Package":"template/models/logic/svclog","Output":"ok  \ttemplate/models/logic/svclog\t(cached)\tcoverage: 54.7% of statements\n"}
{"Time":"2018-10-24T12:32:59.63130887+07:00","Action":"pass","Package":"template/models/logic/svclog","Elapsed":0}
{"Time":"2018-10-24T13:52:43.376216619+07:00","Action":"run","Package":"template/models/logic/svclog","Test":"TestInsertServiceLog"}
{"Time":"2018-10-24T13:52:43.376312996+07:00","Action":"output","Package":"template/models/logic/svclog","Test":"TestInsertServiceLog","Output":"=== RUN   TestInsertServiceLog\n"}
{"Time":"2018-10-24T13:52:43.376320533+07:00","Action":"output","Package":"template/models/logic/svclog","Test":"TestInsertServiceLog","Output":"[ORM]2018/10/24 12:30:55  -[Queries/default] - [  OK /  db.BeginTx /     0.0ms] - [START TRANSACTION]\n"}
{"Time":"2018-10-24T13:52:43.37632565+07:00","Action":"output","Package":"template/models/logic/svclog","Test":"TestInsertServiceLog","Output":"[ORM]2018/10/24 12:30:55  -[Queries/default] - [  OK /   tx.Commit /     0.1ms] - [COMMIT]\n"}
{"Time":"2018-10-24T13:52:43.376330421+07:00","Action":"output","Package":"template/models/logic/svclog","Test":"TestInsertServiceLog","Output":"\n"}
{"Time":"2018-10-24T13:52:43.376334959+07:00","Action":"output","Package":"template/models/logic/svclog","Test":"TestInsertServiceLog","Output":"  TestInsertServiceLog \n"}
{"Time":"2018-10-24T13:52:43.376339574+07:00","Action":"output","Package":"template/models/logic/svclog","Test":"TestInsertServiceLog","Output":"    Should Success \u001b[32m✔\u001b[0m\n"}
{"Time":"2018-10-24T13:52:43.376344217+07:00","Action":"output","Package":"template/models/logic/svclog","Test":"TestInsertServiceLog","Output":"\n"}
{"Time":"2018-10-24T13:52:43.376348462+07:00","Action":"output","Package":"template/models/logic/svclog","Test":"TestInsertServiceLog","Output":"\u001b[31m\u001b[0m\u001b[33m\u001b[0m\u001b[32m\n"}
{"Time":"2018-10-24T13:52:43.376353341+07:00","Action":"output","Package":"template/models/logic/svclog","Test":"TestInsertServiceLog","Output":"1 total assertion\u001b[0m\n"}
{"Time":"2018-10-24T13:52:43.376358598+07:00","Action":"output","Package":"template/models/logic/svclog","Test":"TestInsertServiceLog","Output":"\n"}
{"Time":"2018-10-24T13:52:43.37636471+07:00","Action":"output","Package":"template/models/logic/svclog","Test":"TestInsertServiceLog","Output":"--- PASS: TestInsertServiceLog (0.00s)\n"}
{"Time":"2018-10-24T13:52:43.376369343+07:00","Action":"pass","Package":"template/models/logic/svclog","Test":"TestInsertServiceLog","Elapsed":0}
{"Time":"2018-10-24T13:52:43.376378017+07:00","Action":"run","Package":"template/models/logic/svclog","Test":"TestGetAllServiceLog"}
{"Time":"2018-10-24T13:52:43.376381761+07:00","Action":"output","Package":"template/models/logic/svclog","Test":"TestGetAllServiceLog","Output":"=== RUN   TestGetAllServiceLog\n"}
{"Time":"2018-10-24T13:52:43.376385589+07:00","Action":"output","Package":"template/models/logic/svclog","Test":"TestGetAllServiceLog","Output":"\n"}
{"Time":"2018-10-24T13:52:43.376389287+07:00","Action":"output","Package":"template/models/logic/svclog","Test":"TestGetAllServiceLog","Output":"  TestGetAllServiceLog \n"}
{"Time":"2018-10-24T13:52:43.376392957+07:00","Action":"output","Package":"template/models/logic/svclog","Test":"TestGetAllServiceLog","Output":"    Should Success \u001b[32m✔\u001b[0m\u001b[32m✔\u001b[0m\n"}
{"Time":"2018-10-24T13:52:43.376396806+07:00","Action":"output","Package":"template/models/logic/svclog","Test":"TestGetAllServiceLog","Output":"\n"}
{"Time":"2018-10-24T13:52:43.376400411+07:00","Action":"output","Package":"template/models/logic/svclog","Test":"TestGetAllServiceLog","Output":"\u001b[31m\u001b[0m\u001b[33m\u001b[0m\u001b[32m\n"}
{"Time":"2018-10-24T13:52:43.376404148+07:00","Action":"output","Package":"template/models/logic/svclog","Test":"TestGetAllServiceLog","Output":"3 total assertions\u001b[0m\n"}
{"Time":"2018-10-24T13:52:43.376408224+07:00","Action":"output","Package":"template/models/logic/svclog","Test":"TestGetAllServiceLog","Output":"\n"}
{"Time":"2018-10-24T13:52:43.376412547+07:00","Action":"output","Package":"template/models/logic/svclog","Test":"TestGetAllServiceLog","Output":"--- PASS: TestGetAllServiceLog (0.00s)\n"}
{"Time":"2018-10-24T13:52:43.376416686+07:00","Action":"pass","Package":"template/models/logic/svclog","Test":"TestGetAllServiceLog","Elapsed":0}
{"Time":"2018-10-24T13:52:43.376420181+07:00","Action":"run","Package":"template/models/logic/svclog","Test":"TestGetOneByJobIDServiceLog"}
{"Time":"2018-10-24T13:52:43.376423569+07:00","Action":"output","Package":"template/models/logic/svclog","Test":"TestGetOneByJobIDServiceLog","Output":"=== RUN   TestGetOneByJobIDServiceLog\n"}
{"Time":"2018-10-24T13:52:43.376427975+07:00","Action":"output","Package":"template/models/logic/svclog","Test":"TestGetOneByJobIDServiceLog","Output":"\n"}
{"Time":"2018-10-24T13:52:43.376431851+07:00","Action":"output","Package":"template/models/logic/svclog","Test":"TestGetOneByJobIDServiceLog","Output":"  TestGetOneByJobIDServiceLog \n"}
{"Time":"2018-10-24T13:52:43.376435626+07:00","Action":"output","Package":"template/models/logic/svclog","Test":"TestGetOneByJobIDServiceLog","Output":"    Should Success \u001b[32m✔\u001b[0m\u001b[32m✔\u001b[0m\n"}
{"Time":"2018-10-24T13:52:43.376439622+07:00","Action":"output","Package":"template/models/logic/svclog","Test":"TestGetOneByJobIDServiceLog","Output":"\n"}
{"Time":"2018-10-24T13:52:43.376443233+07:00","Action":"output","Package":"template/models/logic/svclog","Test":"TestGetOneByJobIDServiceLog","Output":"\u001b[31m\u001b[0m\u001b[33m\u001b[0m\u001b[32m\n"}
{"Time":"2018-10-24T13:52:43.37644692+07:00","Action":"output","Package":"template/models/logic/svclog","Test":"TestGetOneByJobIDServiceLog","Output":"5 total assertions\u001b[0m\n"}
{"Time":"2018-10-24T13:52:43.376450603+07:00","Action":"output","Package":"template/models/logic/svclog","Test":"TestGetOneByJobIDServiceLog","Output":"\n"}
{"Time":"2018-10-24T13:52:43.376454747+07:00","Action":"output","Package":"template/models/logic/svclog","Test":"TestGetOneByJobIDServiceLog","Output":"--- PASS: TestGetOneByJobIDServiceLog (0.00s)\n"}
{"Time":"2018-10-24T13:52:43.376458803+07:00","Action":"pass","Package":"template/models/logic/svclog","Test":"TestGetOneByJobIDServiceLog","Elapsed":0}
{"Time":"2018-10-24T13:52:43.376462175+07:00","Action":"run","Package":"template/models/logic/svclog","Test":"TestUpdateByJobIDServiceLog"}
{"Time":"2018-10-24T13:52:43.376465506+07:00","Action":"output","Package":"template/models/logic/svclog","Test":"TestUpdateByJobIDServiceLog","Output":"=== RUN   TestUpdateByJobIDServiceLog\n"}
{"Time":"2018-10-24T13:52:43.37647159+07:00","Action":"output","Package":"template/models/logic/svclog","Test":"TestUpdateByJobIDServiceLog","Output":"[ORM]2018/10/24 12:30:55  -[Queries/default] - [  OK /  db.BeginTx /     0.0ms] - [START TRANSACTION]\n"}
{"Time":"2018-10-24T13:52:43.376496191+07:00","Action":"output","Package":"template/models/logic/svclog","Test":"TestUpdateByJobIDServiceLog","Output":"[ORM]2018/10/24 12:30:55  -[Queries/default] - [  OK /   tx.Commit /     0.0ms] - [COMMIT]\n"}
{"Time":"2018-10-24T13:52:43.376500196+07:00","Action":"output","Package":"template/models/logic/svclog","Test":"TestUpdateByJobIDServiceLog","Output":"\n"}
{"Time":"2018-10-24T13:52:43.376522444+07:00","Action":"output","Package":"template/models/logic/svclog","Test":"TestUpdateByJobIDServiceLog","Output":"  TestUpdateByJobIDServiceLog \n"}
{"Time":"2018-10-24T13:52:43.376526563+07:00","Action":"output","Package":"template/models/logic/svclog","Test":"TestUpdateByJobIDServiceLog","Output":"    Should Success \u001b[32m✔\u001b[0m\n"}
{"Time":"2018-10-24T13:52:43.376530581+07:00","Action":"output","Package":"template/models/logic/svclog","Test":"TestUpdateByJobIDServiceLog","Output":"\n"}
{"Time":"2018-10-24T13:52:43.376535082+07:00","Action":"output","Package":"template/models/logic/svclog","Test":"TestUpdateByJobIDServiceLog","Output":"\u001b[31m\u001b[0m\u001b[33m\u001b[0m\u001b[32m\n"}
{"Time":"2018-10-24T13:52:43.37653912+07:00","Action":"output","Package":"template/models/logic/svclog","Test":"TestUpdateByJobIDServiceLog","Output":"6 total assertions\u001b[0m\n"}
{"Time":"2018-10-24T13:52:43.376542998+07:00","Action":"output","Package":"template/models/logic/svclog","Test":"TestUpdateByJobIDServiceLog","Output":"\n"}
{"Time":"2018-10-24T13:52:43.376560614+07:00","Action":"output","Package":"template/models/logic/svclog","Test":"TestUpdateByJobIDServiceLog","Output":"--- PASS: TestUpdateByJobIDServiceLog (0.00s)\n"}
{"Time":"2018-10-24T13:52:43.376564994+07:00","Action":"pass","Package":"template/models/logic/svclog","Test":"TestUpdateByJobIDServiceLog","Elapsed":0}
{"Time":"2018-10-24T13:52:43.376581797+07:00","Action":"run","Package":"template/models/logic/svclog","Test":"TestUpdateReturnByJobIDServiceLog"}
{"Time":"2018-10-24T13:52:43.376585743+07:00","Action":"output","Package":"template/models/logic/svclog","Test":"TestUpdateReturnByJobIDServiceLog","Output":"=== RUN   TestUpdateReturnByJobIDServiceLog\n"}
{"Time":"2018-10-24T13:52:43.376589963+07:00","Action":"output","Package":"template/models/logic/svclog","Test":"TestUpdateReturnByJobIDServiceLog","Output":"[ORM]2018/10/24 12:30:55  -[Queries/default] - [  OK /  db.BeginTx /     0.0ms] - [START TRANSACTION]\n"}
{"Time":"2018-10-24T13:52:43.376594031+07:00","Action":"output","Package":"template/models/logic/svclog","Test":"TestUpdateReturnByJobIDServiceLog","Output":"[ORM]2018/10/24 12:30:55  -[Queries/default] - [  OK /   tx.Commit /     0.1ms] - [COMMIT]\n"}
{"Time":"2018-10-24T13:52:43.376597767+07:00","Action":"output","Package":"template/models/logic/svclog","Test":"TestUpdateReturnByJobIDServiceLog","Output":"\n"}
{"Time":"2018-10-24T13:52:43.376601475+07:00","Action":"output","Package":"template/models/logic/svclog","Test":"TestUpdateReturnByJobIDServiceLog","Output":"  TestUpdateReturnByJobIDServiceLog \n"}
{"Time":"2018-10-24T13:52:43.3766051+07:00","Action":"output","Package":"template/models/logic/svclog","Test":"TestUpdateReturnByJobIDServiceLog","Output":"    Should Success \u001b[32m✔\u001b[0m\u001b[32m✔\u001b[0m\n"}
{"Time":"2018-10-24T13:52:43.376609024+07:00","Action":"output","Package":"template/models/logic/svclog","Test":"TestUpdateReturnByJobIDServiceLog","Output":"\n"}
{"Time":"2018-10-24T13:52:43.376612628+07:00","Action":"output","Package":"template/models/logic/svclog","Test":"TestUpdateReturnByJobIDServiceLog","Output":"\u001b[31m\u001b[0m\u001b[33m\u001b[0m\u001b[32m\n"}
{"Time":"2018-10-24T13:52:43.37661644+07:00","Action":"output","Package":"template/models/logic/svclog","Test":"TestUpdateReturnByJobIDServiceLog","Output":"8 total assertions\u001b[0m\n"}
{"Time":"2018-10-24T13:52:43.37662209+07:00","Action":"output","Package":"template/models/logic/svclog","Test":"TestUpdateReturnByJobIDServiceLog","Output":"\n"}
{"Time":"2018-10-24T13:52:43.376626357+07:00","Action":"output","Package":"template/models/logic/svclog","Test":"TestUpdateReturnByJobIDServiceLog","Output":"--- PASS: TestUpdateReturnByJobIDServiceLog (0.00s)\n"}
{"Time":"2018-10-24T13:52:43.376630505+07:00","Action":"pass","Package":"template/models/logic/svclog","Test":"TestUpdateReturnByJobIDServiceLog","Elapsed":0}
{"Time":"2018-10-24T13:52:43.376634192+07:00","Action":"run","Package":"template/models/logic/svclog","Test":"TestDeleteByJobIDServiceLog"}
{"Time":"2018-10-24T13:52:43.3766384+07:00","Action":"output","Package":"template/models/logic/svclog","Test":"TestDeleteByJobIDServiceLog","Output":"=== RUN   TestDeleteByJobIDServiceLog\n"}
{"Time":"2018-10-24T13:52:43.376642269+07:00","Action":"output","Package":"template/models/logic/svclog","Test":"TestDeleteByJobIDServiceLog","Output":"[ORM]2018/10/24 12:30:55  -[Queries/default] - [  OK /  db.BeginTx /     0.0ms] - [START TRANSACTION]\n"}
{"Time":"2018-10-24T13:52:43.376646148+07:00","Action":"output","Package":"template/models/logic/svclog","Test":"TestDeleteByJobIDServiceLog","Output":"[ORM]2018/10/24 12:30:55  -[Queries/default] - [  OK /   tx.Commit /     0.1ms] - [COMMIT]\n"}
{"Time":"2018-10-24T13:52:43.376649937+07:00","Action":"output","Package":"template/models/logic/svclog","Test":"TestDeleteByJobIDServiceLog","Output":"\n"}
{"Time":"2018-10-24T13:52:43.376654025+07:00","Action":"output","Package":"template/models/logic/svclog","Test":"TestDeleteByJobIDServiceLog","Output":"  TestDeleteByJobIDServiceLog \n"}
{"Time":"2018-10-24T13:52:43.376657928+07:00","Action":"output","Package":"template/models/logic/svclog","Test":"TestDeleteByJobIDServiceLog","Output":"    Should Success \u001b[32m✔\u001b[0m\n"}
{"Time":"2018-10-24T13:52:43.376661675+07:00","Action":"output","Package":"template/models/logic/svclog","Test":"TestDeleteByJobIDServiceLog","Output":"\n"}
{"Time":"2018-10-24T13:52:43.376665276+07:00","Action":"output","Package":"template/models/logic/svclog","Test":"TestDeleteByJobIDServiceLog","Output":"\u001b[31m\u001b[0m\u001b[33m\u001b[0m\u001b[32m\n"}
{"Time":"2018-10-24T13:52:43.376668995+07:00","Action":"output","Package":"template/models/logic/svclog","Test":"TestDeleteByJobIDServiceLog","Output":"9 total assertions\u001b[0m\n"}
{"Time":"2018-10-24T13:52:43.376672644+07:00","Action":"output","Package":"template/models/logic/svclog","Test":"TestDeleteByJobIDServiceLog","Output":"\n"}
{"Time":"2018-10-24T13:52:43.376676768+07:00","Action":"output","Package":"template/models/logic/svclog","Test":"TestDeleteByJobIDServiceLog","Output":"--- PASS: TestDeleteByJobIDServiceLog (0.00s)\n"}
{"Time":"2018-10-24T13:52:43.376680475+07:00","Action":"pass","Package":"template/models/logic/svclog","Test":"TestDeleteByJobIDServiceLog","Elapsed":0}
{"Time":"2018-10-24T13:52:43.376684334+07:00","Action":"output","Package":"template/models/logic/svclog","Output":"PASS\n"}
{"Time":"2018-10-24T13:52:43.376688197+07:00","Action":"output","Package":"template/models/logic/svclog","Output":"coverage: 54.7% of statements\n"}
{"Time":"2018-10-24T13:52:43.376691845+07:00","Action":"output","Package":"template/models/logic/svclog","Output":"ok  \ttemplate/models/logic/svclog\t(cached)\tcoverage: 54.7% of statements\n"}
{"Time":"2018-10-24T13:52:43.376697285+07:00","Action":"pass","Package":"template/models/logic/svclog","Elapsed":0}
